{
  "project_info": {
    "project_number": "931389886089",
    "project_id": "taskydo-3465f",
    "storage_bucket": "taskydo-3465f.appspot.com"
  },
  "client": [
    {
      "client_info": {
        "mobilesdk_app_id": "1:931389886089:android:c05b6452ac7e6b41038058",
        "android_client_info": {
          "package_name": "com.app.taskydo"
        }
      },
      "oauth_client": [
        {
          "client_id": "931389886089-mi0a74qusgi8m418np46eqk983ces1vt.apps.googleusercontent.com",
          "client_type": 3
        }
      ],
      "api_key": [
        {
          "current_key": "AIzaSyCv_AvpwDhj_gaAxOZXlLtQqQDJeUOO5uE"
        }
      ],
      "services": {
        "appinvite_service": {
          "other_platform_oauth_client": [
            {
              "client_id": "931389886089-mi0a74qusgi8m418np46eqk983ces1vt.apps.googleusercontent.com",
              "client_type": 3
            }
          ]
        }
      }
    }
  ],
  "configuration_version": "1"
}